gspread_formatting/__init__.py
gspread_formatting/batch.py
gspread_formatting/batch_update_requests.py
gspread_formatting/conditionals.py
gspread_formatting/dataframe.py
gspread_formatting/functions.py
gspread_formatting/models.py
gspread_formatting/util.py
gspread_formatting-1.2.0.dist-info/LICENSE
gspread_formatting-1.2.0.dist-info/METADATA
gspread_formatting-1.2.0.dist-info/WHEEL
gspread_formatting-1.2.0.dist-info/top_level.txt
gspread_formatting-1.2.0.dist-info/zip-safe
gspread_formatting-1.2.0.dist-info/RECORD
