Metadata-Version: 2.1
Name: gspread-formatting
Version: 1.2.0
Summary: Complete Google Sheets formatting support for gspread worksheets
Home-page: https://github.com/robin900/gspread-formatting
Author: Robin Thomas
Author-email: rthomas900@gmail.com
License: MIT
Keywords: spreadsheets,google-spreadsheets,formatting,cell-format
Classifier: Programming Language :: Python
Classifier: Programming Language :: Python :: 3
Classifier: Programming Language :: Python :: Implementation :: CPython
Classifier: Programming Language :: Python :: Implementation :: PyPy
Classifier: License :: OSI Approved :: MIT License
Classifier: Operating System :: OS Independent
Classifier: Development Status :: 5 - Production/Stable
Classifier: Intended Audience :: Developers
Classifier: Intended Audience :: Science/Research
Classifier: Topic :: Office/Business :: Financial :: Spreadsheet
Classifier: Topic :: Software Development :: Libraries :: Python Modules
License-File: LICENSE
